marsopt/__init__.py
marsopt/logger.py
marsopt/solver.py
marsopt/variable.py
marsopt-0.1.1.dist-info/licenses/LICENSE
marsopt-0.1.1.dist-info/METADATA
marsopt-0.1.1.dist-info/WHEEL
marsopt-0.1.1.dist-info/top_level.txt
marsopt-0.1.1.dist-info/RECORD
