Metadata-Version: 2.4
Name: marsopt
Version: 0.1.1
Summary: Mixed Adaptive Random Search for Optimization
Author-email: Samet Copur <sametcopur@yahoo.com>, Ilker Birbil <sibirbil@gmail.com>
License: MIT License
Project-URL: Documentation, https://marsopt.readthedocs.io/en/latest/
Project-URL: Repository, https://github.com/sibirbil/marsopt
Project-URL: Tracker, https://github.com/sibirbil/marspot/issues
Keywords: python,optimization,adaptive-random-search,hyperparameter-tuning,hyperparameter-optimization,mixed-parameter-space,categorical-parameters,machine-learning,data-science,metaheuristics
Classifier: Development Status :: 5 - Production/Stable
Classifier: Intended Audience :: Science/Research
Classifier: Intended Audience :: Developers
Classifier: License :: OSI Approved :: MIT License
Classifier: Programming Language :: Python :: 3
Classifier: Programming Language :: Python :: 3.8
Classifier: Programming Language :: Python :: 3.9
Classifier: Programming Language :: Python :: 3.10
Classifier: Programming Language :: Python :: 3.11
Classifier: Programming Language :: Python :: 3.12
Classifier: Programming Language :: Python :: 3.13
Classifier: Programming Language :: Python :: 3 :: Only
Classifier: Topic :: Scientific/Engineering
Classifier: Topic :: Scientific/Engineering :: Mathematics
Classifier: Topic :: Scientific/Engineering :: Artificial Intelligence
Classifier: Topic :: Software Development
Classifier: Topic :: Software Development :: Libraries
Classifier: Topic :: Software Development :: Libraries :: Python Modules
Requires-Python: >=3.8
License-File: LICENSE
Requires-Dist: numpy
Provides-Extra: extra
Requires-Dist: scipy; extra == "extra"
Dynamic: license-file
